complwetion/__init__.py
complwetion/crawler.py
complwetion/vector_db_service.py
complwetion-0.2.1.dist-info/METADATA
complwetion-0.2.1.dist-info/WHEEL
complwetion-0.2.1.dist-info/top_level.txt
complwetion-0.2.1.dist-info/RECORD
